bspl/__init__.py
bspl/langshaw.py
bspl/main.py
bspl/protocol.py
bspl/utils.py
bspl/validation.py
bspl/adapter/__init__.py
bspl/adapter/core.py
bspl/adapter/emitter.py
bspl/adapter/event.py
bspl/adapter/jason.py
bspl/adapter/message.py
bspl/adapter/policies.py
bspl/adapter/policy.gr
bspl/adapter/receiver.py
bspl/adapter/scheduler.py
bspl/adapter/schema.py
bspl/adapter/statistics.py
bspl/adapter/store.py
bspl/generators/__init__.py
bspl/generators/asl.py
bspl/generators/mambo.py
bspl/generators/node_red.py
bspl/parsers/bspl/__init__.py
bspl/parsers/bspl/bspl.gr
bspl/parsers/bspl/bspl_parser.py
bspl/parsers/bspl/build.py
bspl/parsers/langshaw/__init__.py
bspl/parsers/langshaw/build.py
bspl/parsers/langshaw/langshaw.gr
bspl/parsers/precedence/__init__.py
bspl/parsers/precedence/precedence.gr
bspl/verification/__init__.py
bspl/verification/logic.py
bspl/verification/lpaths.py
bspl/verification/mambo.py
bspl/verification/paths.py
bspl/verification/precedence.py
bspl/verification/refinement.py
bspl/verification/sat.py
bspl-1.0.0.dist-info/licenses/LICENSE
bspl-1.0.0.dist-info/METADATA
bspl-1.0.0.dist-info/WHEEL
bspl-1.0.0.dist-info/entry_points.txt
bspl-1.0.0.dist-info/top_level.txt
bspl-1.0.0.dist-info/RECORD
