Metadata-Version: 2.4
Name: bspl
Version: 1.0.0
Summary: Protocol verification tool for BSPL
Home-page: https://gitlab.com/masr/bspl
Author: Samuel Christie
Author-email: shcv@sdf.org
Project-URL: Bug Reports, https://gitlab.com/masr/bspl/-/issues
Project-URL: Source, https://gitlab.com/masr/bspl
Classifier: Development Status :: 5 - Production/Stable
Classifier: Intended Audience :: Developers
Classifier: Programming Language :: Python :: 3
Classifier: Programming Language :: Python :: 3.8
Classifier: Programming Language :: Python :: 3.9
Classifier: Programming Language :: Python :: 3.10
Classifier: Programming Language :: Python :: 3.11
Classifier: License :: OSI Approved :: MIT License
Classifier: Topic :: Software Development :: Libraries :: Python Modules
Classifier: Topic :: Utilities
Requires-Python: >=3.8
License-File: LICENSE
Requires-Dist: TatSu
Requires-Dist: simplejson
Requires-Dist: ttictoc
Requires-Dist: fire
Requires-Dist: aiocron
Requires-Dist: croniter
Requires-Dist: pyyaml
Requires-Dist: ijson
Requires-Dist: aiorun
Requires-Dist: uvloop; sys_platform != "win32"
Requires-Dist: colorama
Requires-Dist: agentspeak
Provides-Extra: testing
Requires-Dist: pytest; extra == "testing"
Provides-Extra: sat
Requires-Dist: boolexpr; extra == "sat"
Provides-Extra: jason
Requires-Dist: agentspeak; extra == "jason"
Provides-Extra: experiments
Requires-Dist: spearmint; extra == "experiments"
Dynamic: license-file
